<?xml version="1.0"?>

<portlet-app xmlns="http://java.sun.com/xml/ns/portlet/portlet-app_2_0.xsd" xmlns:xsi="http://www.w3.org/2001/XMLSchema-instance" xsi:schemaLocation="http://java.sun.com/xml/ns/portlet/portlet-app_2_0.xsd http://java.sun.com/xml/ns/portlet/portlet-app_2_0.xsd" version="2.0">

	<portlet>
		<portlet-name>home</portlet-name>
		<display-name>Home Portlet</display-name>
		<portlet-class>com.app.portlets.HomePortlet</portlet-class>
		<init-param>
			<name>view-template</name>
			<value>/html/home/HomeView.jsp</value>
		</init-param>
		<expiration-cache>0</expiration-cache>
		<supports>
			<mime-type>text/html</mime-type>
			<portlet-mode>view</portlet-mode>
		</supports>
		<resource-bundle>content/System</resource-bundle>
		<portlet-info>
			<title>Home Portlet</title>
			<short-title>Home Portlet</short-title>
			<keywords></keywords>
		</portlet-info>
		<security-role-ref>
			<role-name>administrator</role-name>
		</security-role-ref>
		<security-role-ref>
			<role-name>guest</role-name>
		</security-role-ref>
		<security-role-ref>
			<role-name>power-user</role-name>
		</security-role-ref>
		<security-role-ref>
			<role-name>user</role-name>
		</security-role-ref>
	</portlet>
	
	<portlet>
		<portlet-name>activate-account</portlet-name>
		<display-name>Activate Account</display-name>
		<portlet-class>com.app.portlets.ActivateAccount</portlet-class>
		<init-param>
			<name>view-template</name>
			<value>/html/activateaccount/activateAccountView.jsp</value>
		</init-param>
		<expiration-cache>0</expiration-cache>
		<supports>
			<mime-type>text/html</mime-type>
			<portlet-mode>view</portlet-mode>
		</supports>
		<resource-bundle>content/System</resource-bundle>
		<portlet-info>
			<title>Activate Account</title>
			<short-title>Activate Account</short-title>
			<keywords></keywords>
		</portlet-info>
		<security-role-ref>
			<role-name>administrator</role-name>
		</security-role-ref>
		<security-role-ref>
			<role-name>guest</role-name>
		</security-role-ref>
		<security-role-ref>
			<role-name>power-user</role-name>
		</security-role-ref>
		<security-role-ref>
			<role-name>user</role-name>
		</security-role-ref>
	</portlet>
	<portlet>
		<portlet-name>AfterSales</portlet-name>
		<display-name>AfterSales</display-name>
		<portlet-class>com.app.portlets.AfterSales</portlet-class>
		<init-param>
			<name>view-template</name>
			<value>/html/aftersales/AfterSalesView.jsp</value>
		</init-param>
		<expiration-cache>0</expiration-cache>
		<supports>
			<mime-type>text/html</mime-type>
			<portlet-mode>view</portlet-mode>
		</supports>
		<resource-bundle>content/System</resource-bundle>
		<portlet-info>
			<title>AfterSales</title>
			<short-title>After Sales</short-title>
			<keywords></keywords>
		</portlet-info>
		<security-role-ref>
			<role-name>administrator</role-name>
		</security-role-ref>
		<security-role-ref>
			<role-name>guest</role-name>
		</security-role-ref>
		<security-role-ref>
			<role-name>power-user</role-name>
		</security-role-ref>
		<security-role-ref>
			<role-name>user</role-name>
		</security-role-ref>
	</portlet>
	<portlet>
		<portlet-name>Billing</portlet-name>
		<display-name>Billing</display-name>
		<portlet-class>com.app.portlets.Billing</portlet-class>
		<init-param>
			<name>view-template</name>
			<value>/html/billing/view.jsp</value>
		</init-param>
		<expiration-cache>0</expiration-cache>
		<supports>
			<mime-type>text/html</mime-type>
			<portlet-mode>view</portlet-mode>
		</supports>
		<resource-bundle>content/System</resource-bundle>
		<portlet-info>
			<title>Billing</title>
			<short-title>Billing</short-title>
			<keywords></keywords>
		</portlet-info>
		<security-role-ref>
			<role-name>administrator</role-name>
		</security-role-ref>
		<security-role-ref>
			<role-name>guest</role-name>
		</security-role-ref>
		<security-role-ref>
			<role-name>power-user</role-name>
		</security-role-ref>
		<security-role-ref>
			<role-name>user</role-name>
		</security-role-ref>
	</portlet>
	
	<portlet>
		<portlet-name>Credits</portlet-name>
		<display-name>Credits</display-name>
		<portlet-class>com.app.portlets.Credits</portlet-class>
		<init-param>
			<name>view-template</name>
			<value>/html/credits/CreditsView.jsp</value>
		</init-param>
		<expiration-cache>0</expiration-cache>
		<supports>
			<mime-type>text/html</mime-type>
			<portlet-mode>view</portlet-mode>
		</supports>
		<resource-bundle>content/System</resource-bundle>
		<portlet-info>
			<title>Credits</title>
			<short-title>Credits</short-title>
			<keywords></keywords>
		</portlet-info>
		<security-role-ref>
			<role-name>administrator</role-name>
		</security-role-ref>
		<security-role-ref>
			<role-name>guest</role-name>
		</security-role-ref>
		<security-role-ref>
			<role-name>power-user</role-name>
		</security-role-ref>
		<security-role-ref>
			<role-name>user</role-name>
		</security-role-ref>
	</portlet>
	
	<portlet>
		<portlet-name>EventListing</portlet-name>
		<display-name>Event Listing</display-name>
		<portlet-class>com.app.portlets.EventListing</portlet-class>
		<init-param>
			<name>view-template</name>
			<value>/html/eventlisting/EventListingView.jsp</value>
		</init-param>
		<expiration-cache>0</expiration-cache>
		<supports>
			<mime-type>text/html</mime-type>
			<portlet-mode>view</portlet-mode>
		</supports>
		<resource-bundle>content/System</resource-bundle>
		<portlet-info>
			<title>Event Listing</title>
			<short-title>Event Listing</short-title>
			<keywords></keywords>
		</portlet-info>
		<security-role-ref>
			<role-name>administrator</role-name>
		</security-role-ref>
		<security-role-ref>
			<role-name>guest</role-name>
		</security-role-ref>
		<security-role-ref>
			<role-name>power-user</role-name>
		</security-role-ref>
		<security-role-ref>
			<role-name>user</role-name>
		</security-role-ref>
	</portlet>
	
	<portlet>
		<portlet-name>Favourites</portlet-name>
		<display-name>Favourites</display-name>
		<portlet-class>com.app.portlets.Favourites</portlet-class>
		<init-param>
			<name>view-template</name>
			<value>/html/favourites/FavouritesView.jsp</value>
		</init-param>
		<expiration-cache>0</expiration-cache>
		<supports>
			<mime-type>text/html</mime-type>
			<portlet-mode>view</portlet-mode>
		</supports>
		<resource-bundle>content/System</resource-bundle>
		<portlet-info>
			<title>Favourites</title>
			<short-title>Favourites</short-title>
			<keywords></keywords>
		</portlet-info>
		<security-role-ref>
			<role-name>administrator</role-name>
		</security-role-ref>
		<security-role-ref>
			<role-name>guest</role-name>
		</security-role-ref>
		<security-role-ref>
			<role-name>power-user</role-name>
		</security-role-ref>
		<security-role-ref>
			<role-name>user</role-name>
		</security-role-ref>
	</portlet>
	
	<portlet>
		<portlet-name>ForgotPassword</portlet-name>
		<display-name>Forgot Password</display-name>
		<portlet-class>com.app.portlets.ForgotPassword</portlet-class>
		<init-param>
			<name>view-template</name>
			<value>/html/forgotpassword/ForgotPasswordView.jsp</value>
		</init-param>
		<expiration-cache>0</expiration-cache>
		<supports>
			<mime-type>text/html</mime-type>
			<portlet-mode>view</portlet-mode>
		</supports>
		<resource-bundle>content/System</resource-bundle>
		<portlet-info>
			<title>Forgot Password</title>
			<short-title>Forgot Password</short-title>
			<keywords></keywords>
		</portlet-info>
		<security-role-ref>
			<role-name>administrator</role-name>
		</security-role-ref>
		<security-role-ref>
			<role-name>guest</role-name>
		</security-role-ref>
		<security-role-ref>
			<role-name>power-user</role-name>
		</security-role-ref>
		<security-role-ref>
			<role-name>user</role-name>
		</security-role-ref>
	</portlet>	
	
	<portlet>
		<portlet-name>invitefriend</portlet-name>
		<display-name>Invite Friend Portlet</display-name>
		<portlet-class>
			com.app.portlets.InviteFriendPortlet
		</portlet-class>
		<init-param>
			<name>view-template</name>
			<value>/html/invitefriend/InviteFriendView.jsp</value>
		</init-param>
		<expiration-cache>0</expiration-cache>
		<supports>
			<mime-type>text/html</mime-type>
			<portlet-mode>view</portlet-mode>
		</supports>
		<resource-bundle>content/System</resource-bundle>
		<portlet-info>
			<title>Invite Friend Portlet</title>
			<short-title>Invite Friend Portlet</short-title>
			<keywords></keywords>
		</portlet-info>
		<security-role-ref>
			<role-name>administrator</role-name>
		</security-role-ref>
		<security-role-ref>
			<role-name>guest</role-name>
		</security-role-ref>
		<security-role-ref>
			<role-name>power-user</role-name>
		</security-role-ref>
		<security-role-ref>
			<role-name>user</role-name>
		</security-role-ref>
	</portlet>
	
	<portlet>
		<portlet-name>inviteregistration</portlet-name>
		<display-name>Invite Registration Portlet</display-name>
		<portlet-class>
			com.app.portlets.InviteRegistrationPortlet
		</portlet-class>
		<init-param>
			<name>view-template</name>
			<value>/html/inviteregistration/InviteRegistrationView.jsp</value>
		</init-param>
		<expiration-cache>0</expiration-cache>
		<supports>
			<mime-type>text/html</mime-type>
			<portlet-mode>view</portlet-mode>
		</supports>
		<resource-bundle>content/System</resource-bundle>
		<portlet-info>
			<title>Invite Registration Portlet</title>
			<short-title>Invite Registration Portlet</short-title>
			<keywords></keywords>
		</portlet-info>
		<security-role-ref>
			<role-name>administrator</role-name>
		</security-role-ref>
		<security-role-ref>
			<role-name>guest</role-name>
		</security-role-ref>
		<security-role-ref>
			<role-name>power-user</role-name>
		</security-role-ref>
		<security-role-ref>
			<role-name>user</role-name>
		</security-role-ref>
	</portlet>
	
	<portlet>
		<portlet-name>orderhistory</portlet-name>
		<display-name>Order History Portlet</display-name>
		<portlet-class>
			com.app.portlets.OrderHistoryPortlet
		</portlet-class>
		<init-param>
			<name>view-template</name>
			<value>/html/orderhistory/OrderHistoryView.jsp</value>
		</init-param>
		<expiration-cache>0</expiration-cache>
		<supports>
			<mime-type>text/html</mime-type>
			<portlet-mode>view</portlet-mode>
		</supports>
		<resource-bundle>content/System</resource-bundle>
		<portlet-info>
			<title>Order History Portlet</title>
			<short-title>Order History Portlet</short-title>
			<keywords></keywords>
		</portlet-info>
		<security-role-ref>
			<role-name>administrator</role-name>
		</security-role-ref>
		<security-role-ref>
			<role-name>guest</role-name>
		</security-role-ref>
		<security-role-ref>
			<role-name>power-user</role-name>
		</security-role-ref>
		<security-role-ref>
			<role-name>user</role-name>
		</security-role-ref>
	</portlet>
	
	<portlet>
		<portlet-name>payment</portlet-name>
		<display-name>Payment</display-name>
		<portlet-class>org.springframework.web.portlet.DispatcherPortlet</portlet-class>
		<init-param>
			<name>contextConfigLocation</name>
			<value>/WEB-INF/payment-portlet.xml</value>
		</init-param>
		<init-param>
			<name>view-template</name>
			<value>/html/payment/PaymentView.jsp</value>
		</init-param>
		<expiration-cache>0</expiration-cache>
		<supports>
			<mime-type>text/html</mime-type>
			<portlet-mode>view</portlet-mode>
		</supports>
		<resource-bundle>content/System</resource-bundle>
		<portlet-info>
			<title>Payment</title>
			<short-title>Payment</short-title>
			<keywords></keywords>
		</portlet-info>
		<security-role-ref>
			<role-name>administrator</role-name>
		</security-role-ref>
		<security-role-ref>
			<role-name>guest</role-name>
		</security-role-ref>
		<security-role-ref>
			<role-name>power-user</role-name>
		</security-role-ref>
		<security-role-ref>
			<role-name>user</role-name>
		</security-role-ref>
	</portlet>
	<portlet>
		<portlet-name>paymentsummary</portlet-name>
		<display-name>paymentsummary</display-name>
		<portlet-class>org.springframework.web.portlet.DispatcherPortlet</portlet-class>
		<init-param>
			<name>contextConfigLocation</name>
			<value>/WEB-INF/paymentsummary-portlet.xml</value>
		</init-param>
		<init-param>
			<name>view-template</name>
			<value>/html/paymentsummary/PaymentSummaryView.jsp</value>
		</init-param>
		<expiration-cache>0</expiration-cache>
		<supports>
			<mime-type>text/html</mime-type>
			<portlet-mode>view</portlet-mode>
		</supports>
		<resource-bundle>content/System</resource-bundle>
		<portlet-info>
			<title>Payment Summary</title>
			<short-title>Payment Summary</short-title>
			<keywords></keywords>
		</portlet-info>
		<security-role-ref>
			<role-name>administrator</role-name>
		</security-role-ref>
		<security-role-ref>
			<role-name>guest</role-name>
		</security-role-ref>
		<security-role-ref>
			<role-name>power-user</role-name>
		</security-role-ref>
		<security-role-ref>
			<role-name>user</role-name>
		</security-role-ref>
	</portlet>
	<portlet>
		<portlet-name>hdfcresponse</portlet-name>
		<display-name>HDFC Response</display-name>
		<portlet-class>org.springframework.web.portlet.DispatcherPortlet</portlet-class>
		<init-param>
			<name>contextConfigLocation</name>
			<value>/WEB-INF/hdfcresponse-portlet.xml</value>
		</init-param>
		<init-param>
			<name>view-template</name>
			<value>/html/payment/HDFCResponseToConfirmation.jsp</value>
		</init-param>
		<expiration-cache>0</expiration-cache>
		<supports>
			<mime-type>text/html</mime-type>
			<portlet-mode>view</portlet-mode>
		</supports>
		<resource-bundle>content/System</resource-bundle>
		<portlet-info>
			<title>HDFC Response</title>
			<short-title>HDFC Response</short-title>
			<keywords></keywords>
		</portlet-info>
		<security-role-ref>
			<role-name>administrator</role-name>
		</security-role-ref>
		<security-role-ref>
			<role-name>guest</role-name>
		</security-role-ref>
		<security-role-ref>
			<role-name>power-user</role-name>
		</security-role-ref>
		<security-role-ref>
			<role-name>user</role-name>
		</security-role-ref>
	</portlet>
	<portlet>
		<portlet-name>productdetail</portlet-name>
		<display-name>Product Detail Portlet</display-name>
		<portlet-class>com.app.portlets.ProductDetailPortlet</portlet-class>
		<init-param>
			<name>view-template</name>
			<value>/html/productdetail/view.jsp</value>
		</init-param>
		<expiration-cache>0</expiration-cache>
		<supports>
			<mime-type>text/html</mime-type>
			<portlet-mode>view</portlet-mode>
		</supports>
		<resource-bundle>content/System</resource-bundle>
		<portlet-info>
			<title>Product Detail Portlet</title>
			<short-title>Product Detail Portlet</short-title>
			<keywords></keywords>
		</portlet-info>
		<security-role-ref>
			<role-name>administrator</role-name>
		</security-role-ref>
		<security-role-ref>
			<role-name>guest</role-name>
		</security-role-ref>
		<security-role-ref>
			<role-name>power-user</role-name>
		</security-role-ref>
		<security-role-ref>
			<role-name>user</role-name>
		</security-role-ref>
	</portlet>
	
	<portlet>
		<portlet-name>restorepassword</portlet-name>
		<display-name>Restore Password Portlet</display-name>
		<portlet-class>
			com.app.portlets.RestorePasswordPortlet
		</portlet-class>
		<init-param>
			<name>view-template</name>
			<value>/html/restorepassword/RestorePasswordView.jsp</value>
		</init-param>
		<expiration-cache>0</expiration-cache>
		<supports>
			<mime-type>text/html</mime-type>
			<portlet-mode>view</portlet-mode>
		</supports>
		<resource-bundle>content/System</resource-bundle>
		<portlet-info>
			<title>Restore Password Portlet</title>
			<short-title>Restore Password Portlet</short-title>
			<keywords></keywords>
		</portlet-info>
		<security-role-ref>
			<role-name>administrator</role-name>
		</security-role-ref>
		<security-role-ref>
			<role-name>guest</role-name>
		</security-role-ref>
		<security-role-ref>
			<role-name>power-user</role-name>
		</security-role-ref>
		<security-role-ref>
			<role-name>user</role-name>
		</security-role-ref>
	</portlet>
	<portlet>
		<portlet-name>rewards</portlet-name>
		<display-name>Rewards Portlet</display-name>
		<portlet-class>com.app.portlets.RewardsPortlet</portlet-class>
		<init-param>
			<name>view-template</name>
			<value>/html/rewards/RewardsView.jsp</value>
		</init-param>
		<expiration-cache>0</expiration-cache>
		<supports>
			<mime-type>text/html</mime-type>
			<portlet-mode>view</portlet-mode>
		</supports>
		<resource-bundle>content/System</resource-bundle>
		<portlet-info>
			<title>Rewards Portlet</title>
			<short-title>Rewards Portlet</short-title>
			<keywords></keywords>
		</portlet-info>
		<security-role-ref>
			<role-name>administrator</role-name>
		</security-role-ref>
		<security-role-ref>
			<role-name>guest</role-name>
		</security-role-ref>
		<security-role-ref>
			<role-name>power-user</role-name>
		</security-role-ref>
		<security-role-ref>
			<role-name>user</role-name>
		</security-role-ref>
	</portlet>
	
	<portlet>
		<portlet-name>search</portlet-name>
		<display-name>Search Portlet</display-name>
		<portlet-class>com.app.portlets.SearchPortlet</portlet-class>
		<init-param>
			<name>view-template</name>
			<value>/html/search/SearchView.jsp</value>
		</init-param>
		<expiration-cache>0</expiration-cache>
		<supports>
			<mime-type>text/html</mime-type>
			<portlet-mode>view</portlet-mode>
		</supports>
		<resource-bundle>content/System</resource-bundle>
		<portlet-info>
			<title>Search Portlet</title>
			<short-title>Search Portlet</short-title>
			<keywords></keywords>
		</portlet-info>
		<security-role-ref>
			<role-name>administrator</role-name>
		</security-role-ref>
		<security-role-ref>
			<role-name>guest</role-name>
		</security-role-ref>
		<security-role-ref>
			<role-name>power-user</role-name>
		</security-role-ref>
		<security-role-ref>
			<role-name>user</role-name>
		</security-role-ref>
	</portlet>
	
	<portlet>
		<portlet-name>userlogin</portlet-name>
		<display-name>User Login Portlet</display-name>
		<portlet-class>com.app.portlets.UserLoginPortlet</portlet-class>
		<init-param>
			<name>view-template</name>
			<value>/html/userlogin/UserloginView.jsp</value>
		</init-param>
		<expiration-cache>0</expiration-cache>
		<supports>
			<mime-type>text/html</mime-type>
			<portlet-mode>view</portlet-mode>
		</supports>
		<resource-bundle>content/System</resource-bundle>
		<portlet-info>
			<title>User Login Portlet</title>
			<short-title>User Login Portlet</short-title>
			<keywords></keywords>
		</portlet-info>
		<security-role-ref>
			<role-name>administrator</role-name>
		</security-role-ref>
		<security-role-ref>
			<role-name>guest</role-name>
		</security-role-ref>
		<security-role-ref>
			<role-name>power-user</role-name>
		</security-role-ref>
		<security-role-ref>
			<role-name>user</role-name>
		</security-role-ref>
	</portlet>
	<portlet>
		<portlet-name>userregistration</portlet-name>
		<display-name>User Registration Portlet</display-name>
		<portlet-class>
			com.app.portlets.UserRegistrationPortlet
		</portlet-class>
		<init-param>
			<name>view-template</name>
			<value>/html/userregistration/UserregistrationView.jsp</value>
		</init-param>
		<expiration-cache>0</expiration-cache>
		<supports>
			<mime-type>text/html</mime-type>
			<portlet-mode>view</portlet-mode>
		</supports>
		<resource-bundle>content/System</resource-bundle>
		<portlet-info>
			<title>User Registration Portlet</title>
			<short-title>User Registration Portlet</short-title>
			<keywords></keywords>
		</portlet-info>
		<security-role-ref>
			<role-name>administrator</role-name>
		</security-role-ref>
		<security-role-ref>
			<role-name>guest</role-name>
		</security-role-ref>
		<security-role-ref>
			<role-name>power-user</role-name>
		</security-role-ref>
		<security-role-ref>
			<role-name>user</role-name>
		</security-role-ref>
	</portlet>
	
	<portlet>
		<portlet-name>vouchers</portlet-name>
		<display-name>Vouchers Portlet</display-name>
		<portlet-class>com.app.portlets.VouchersPortlet</portlet-class>
		<init-param>
			<name>view-template</name>
			<value>/html/vouchers/VouchersView.jsp</value>
		</init-param>
		<expiration-cache>0</expiration-cache>
		<supports>
			<mime-type>text/html</mime-type>
			<portlet-mode>view</portlet-mode>
		</supports>
		<resource-bundle>content/System</resource-bundle>
		<portlet-info>
			<title>Vouchers Portlet</title>
			<short-title>Vouchers Portlet</short-title>
			<keywords></keywords>
		</portlet-info>
		<security-role-ref>
			<role-name>administrator</role-name>
		</security-role-ref>
		<security-role-ref>
			<role-name>guest</role-name>
		</security-role-ref>
		<security-role-ref>
			<role-name>power-user</role-name>
		</security-role-ref>
		<security-role-ref>
			<role-name>user</role-name>
		</security-role-ref>
	</portlet>

	<portlet>
		<portlet-name>electronictag</portlet-name>
		<display-name>Electronic Tag Portlet</display-name>
		<portlet-class>com.app.portlets.ElectronicTagPortlet</portlet-class>
		<init-param>
			<name>view-template</name>
			<value>/html/electronictag/ElectronicView.jsp</value>
		</init-param>
		<expiration-cache>0</expiration-cache>
		<supports>
			<mime-type>text/html</mime-type>
			<portlet-mode>view</portlet-mode>
		</supports>
		<resource-bundle>content/System</resource-bundle>
		<portlet-info>
			<title>Electronic Tag Portlet</title>
			<short-title>Electronic Tag Portlet</short-title>
			<keywords></keywords>
		</portlet-info>
		<security-role-ref>
			<role-name>administrator</role-name>
		</security-role-ref>
		<security-role-ref>
			<role-name>guest</role-name>
		</security-role-ref>
		<security-role-ref>
			<role-name>power-user</role-name>
		</security-role-ref>
		<security-role-ref>
			<role-name>user</role-name>
		</security-role-ref>
	</portlet>
	<portlet>
		<portlet-name>pressrelease</portlet-name>
		<display-name>Press Release Portlet</display-name>
		<portlet-class>com.app.portlets.PressReleasePortlet</portlet-class>
		<init-param>
			<name>view-template</name>
			<value>/html/pressrelease/PressreleaseView.jsp</value>
		</init-param>
		<expiration-cache>0</expiration-cache>
		<supports>
			<mime-type>text/html</mime-type>
			<portlet-mode>view</portlet-mode>
		</supports>
		<resource-bundle>content/System</resource-bundle>
		<portlet-info>
			<title>Press Release Portlet</title>
			<short-title>Press Release Portlet</short-title>
			<keywords></keywords>
		</portlet-info>
		<security-role-ref>
			<role-name>administrator</role-name>
		</security-role-ref>
		<security-role-ref>
			<role-name>guest</role-name>
		</security-role-ref>
		<security-role-ref>
			<role-name>power-user</role-name>
		</security-role-ref>
		<security-role-ref>
			<role-name>user</role-name>
		</security-role-ref>
	</portlet>
	<portlet>
		<portlet-name>printtag</portlet-name>
		<display-name>Print Tag Portlet</display-name>
		<portlet-class>com.app.portlets.PrintTagPortlet</portlet-class>
		<init-param>
			<name>view-template</name>
			<value>/html/printtag/PrintView.jsp</value>
		</init-param>
		<expiration-cache>0</expiration-cache>
		<supports>
			<mime-type>text/html</mime-type>
			<portlet-mode>view</portlet-mode>
		</supports>
		<resource-bundle>content/System</resource-bundle>
		<portlet-info>
			<title>Print Tag Portlet</title>
			<short-title>Print Tag Portlet</short-title>
			<keywords></keywords>
		</portlet-info>
		<security-role-ref>
			<role-name>administrator</role-name>
		</security-role-ref>
		<security-role-ref>
			<role-name>guest</role-name>
		</security-role-ref>
		<security-role-ref>
			<role-name>power-user</role-name>
		</security-role-ref>
		<security-role-ref>
			<role-name>user</role-name>
		</security-role-ref>
	</portlet>
	<portlet>
		<portlet-name>digitaltag</portlet-name>
		<display-name>Digital Tag Portlet</display-name>
		<portlet-class>com.app.portlets.DigitalTagPortlet</portlet-class>
		<init-param>
			<name>view-template</name>
			<value>/html/digitaltag/DigitalView.jsp</value>
		</init-param>
		<expiration-cache>0</expiration-cache>
		<supports>
			<mime-type>text/html</mime-type>
			<portlet-mode>view</portlet-mode>
		</supports>
		<resource-bundle>content/System</resource-bundle>
		<portlet-info>
			<title>Digital Tag Portlet</title>
			<short-title>Digital Tag Portlet</short-title>
			<keywords></keywords>
		</portlet-info>
		<security-role-ref>
			<role-name>administrator</role-name>
		</security-role-ref>
		<security-role-ref>
			<role-name>guest</role-name>
		</security-role-ref>
		<security-role-ref>
			<role-name>power-user</role-name>
		</security-role-ref>
		<security-role-ref>
			<role-name>user</role-name>
		</security-role-ref>
	</portlet>
	<portlet>
		<portlet-name>awardstag</portlet-name>
		<display-name>Awards Tag Portlet</display-name>
		<portlet-class>com.app.portlets.AwardsTagPortlet</portlet-class>
		<init-param>
			<name>view-template</name>
			<value>/html/awardstag/AwardsView.jsp</value>
		</init-param>
		<expiration-cache>0</expiration-cache>
		<supports>
			<mime-type>text/html</mime-type>
			<portlet-mode>view</portlet-mode>
		</supports>
		<resource-bundle>content/System</resource-bundle>
		<portlet-info>
			<title>Awards Tag Portlet</title>
			<short-title>Awards Tag Portlet</short-title>
			<keywords></keywords>
		</portlet-info>
		<security-role-ref>
			<role-name>administrator</role-name>
		</security-role-ref>
		<security-role-ref>
			<role-name>guest</role-name>
		</security-role-ref>
		<security-role-ref>
			<role-name>power-user</role-name>
		</security-role-ref>
		<security-role-ref>
			<role-name>user</role-name>
		</security-role-ref>
	</portlet>
	<portlet>
		<portlet-name>category</portlet-name>
		<display-name>Category</display-name>
		<portlet-class>com.app.portlets.Category</portlet-class>
		<init-param>
			<name>view-template</name>
			<value>/html/category/view.jsp</value>
		</init-param>
		<expiration-cache>0</expiration-cache>
		<supports>
			<mime-type>text/html</mime-type>
			<portlet-mode>view</portlet-mode>
		</supports>
		<resource-bundle>content/System</resource-bundle>
		<portlet-info>
			<title>Category</title>
			<short-title>Category</short-title>
			<keywords></keywords>
		</portlet-info>
		<security-role-ref>
			<role-name>administrator</role-name>
		</security-role-ref>
		<security-role-ref>
			<role-name>guest</role-name>
		</security-role-ref>
		<security-role-ref>
			<role-name>power-user</role-name>
		</security-role-ref>
		<security-role-ref>
			<role-name>user</role-name>
		</security-role-ref>
	</portlet>
	<portlet>
		<portlet-name>productlisitng</portlet-name>
		<display-name>Product Lisitng</display-name>
		<portlet-class>com.app.portlets.ProductLisitng</portlet-class>
		<init-param>
			<name>view-template</name>
			<value>/html/productlisitng/view.jsp</value>
		</init-param>
		<expiration-cache>0</expiration-cache>
		<supports>
			<mime-type>text/html</mime-type>
			<portlet-mode>view</portlet-mode>
		</supports>
		<resource-bundle>content/System</resource-bundle>
		<portlet-info>
			<title>Product Lisitng</title>
			<short-title>Product Lisitng</short-title>
			<keywords></keywords>
		</portlet-info>
		<security-role-ref>
			<role-name>administrator</role-name>
		</security-role-ref>
		<security-role-ref>
			<role-name>guest</role-name>
		</security-role-ref>
		<security-role-ref>
			<role-name>power-user</role-name>
		</security-role-ref>
		<security-role-ref>
			<role-name>user</role-name>
		</security-role-ref>
	</portlet>
	<portlet>
		<portlet-name>cart</portlet-name>
		<display-name>Cart</display-name>
		<portlet-class>com.app.portlets.Cart</portlet-class>
		<init-param>
			<name>view-template</name>
			<value>/html/cart/view.jsp</value>
		</init-param>
		<expiration-cache>0</expiration-cache>
		<supports>
			<mime-type>text/html</mime-type>
			<portlet-mode>view</portlet-mode>
		</supports>
		<resource-bundle>content/System</resource-bundle>
		<portlet-info>
			<title>Cart</title>
			<short-title>Cart</short-title>
			<keywords></keywords>
		</portlet-info>
		<security-role-ref>
			<role-name>administrator</role-name>
		</security-role-ref>
		<security-role-ref>
			<role-name>guest</role-name>
		</security-role-ref>
		<security-role-ref>
			<role-name>power-user</role-name>
		</security-role-ref>
		<security-role-ref>
			<role-name>user</role-name>
		</security-role-ref>
	</portlet>
	
	<portlet>
		<portlet-name>profile</portlet-name>
		<display-name>Profile Portlet</display-name>
		<portlet-class>com.app.portlets.ProfilePortlet</portlet-class>
		<init-param>
			<name>view-template</name>
			<value>/html/profile/view.jsp</value>
		</init-param>
		<expiration-cache>0</expiration-cache>
		<supports>
			<mime-type>text/html</mime-type>
			<portlet-mode>view</portlet-mode>
		</supports>
		<resource-bundle>content/System</resource-bundle>
		<portlet-info>
			<title>Profile Portlet</title>
			<short-title>Profile Portlet</short-title>
			<keywords></keywords>
		</portlet-info>
		<security-role-ref>
			<role-name>administrator</role-name>
		</security-role-ref>
		<security-role-ref>
			<role-name>guest</role-name>
		</security-role-ref>
		<security-role-ref>
			<role-name>power-user</role-name>
		</security-role-ref>
		<security-role-ref>
			<role-name>user</role-name>
		</security-role-ref>
	</portlet>
	<portlet>
		<portlet-name>navigation</portlet-name>
		<display-name>Navigation Portlet</display-name>
		<portlet-class>
			com.app.portlets.NavigationPortlet
		</portlet-class>
		<init-param>
			<name>view-template</name>
			<value>/html/navigation/view.jsp</value>
		</init-param>
		<expiration-cache>0</expiration-cache>
		<supports>
			<mime-type>text/html</mime-type>
			<portlet-mode>view</portlet-mode>
		</supports>
		<resource-bundle>content/System</resource-bundle>
		<portlet-info>
			<title>Navigation Portlet</title>
			<short-title>Navigation Portlet</short-title>
			<keywords></keywords>
		</portlet-info>
		<security-role-ref>
			<role-name>administrator</role-name>
		</security-role-ref>
		<security-role-ref>
			<role-name>guest</role-name>
		</security-role-ref>
		<security-role-ref>
			<role-name>power-user</role-name>
		</security-role-ref>
		<security-role-ref>
			<role-name>user</role-name>
		</security-role-ref>
	</portlet>
	<portlet>
		<portlet-name>gettnc</portlet-name>
		<display-name>Get TNC Portlet</display-name>
		<portlet-class>com.app.portlets.GetTNCPortlet</portlet-class>
		<init-param>
			<name>view-template</name>
			<value>/html/gettnc/view.jsp</value>
		</init-param>
		<expiration-cache>0</expiration-cache>
		<supports>
			<mime-type>text/html</mime-type>
			<portlet-mode>view</portlet-mode>
		</supports>
		<portlet-info>
			<title>Get TNC Portlet</title>
			<short-title>Get TNC Portlet</short-title>
			<keywords></keywords>
		</portlet-info>
		<security-role-ref>
			<role-name>administrator</role-name>
		</security-role-ref>
		<security-role-ref>
			<role-name>guest</role-name>
		</security-role-ref>
		<security-role-ref>
			<role-name>power-user</role-name>
		</security-role-ref>
		<security-role-ref>
			<role-name>user</role-name>
		</security-role-ref>
	</portlet>
	<portlet>
		<portlet-name>preview</portlet-name>
		<display-name>Preview Portlet</display-name>
		<portlet-class>com.app.portlets.PreviewPortlet</portlet-class>
		<init-param>
			<name>view-template</name>
			<value>/html/preview/PreviewView.jsp</value>
		</init-param>
		<expiration-cache>0</expiration-cache>
		<supports>
			<mime-type>text/html</mime-type>
			<portlet-mode>view</portlet-mode>
		</supports>
		<resource-bundle>content/System</resource-bundle>
		<portlet-info>
			<title>Preview Portlet</title>
			<short-title>Preview Portlet</short-title>
			<keywords></keywords>
		</portlet-info>
		<security-role-ref>
			<role-name>administrator</role-name>
		</security-role-ref>
		<security-role-ref>
			<role-name>guest</role-name>
		</security-role-ref>
		<security-role-ref>
			<role-name>power-user</role-name>
		</security-role-ref>
		<security-role-ref>
			<role-name>user</role-name>
		</security-role-ref>
	</portlet>
	 <portlet>
		<portlet-name>previewcategory</portlet-name>
		<display-name>Preview Category Portlet</display-name>
		<portlet-class>com.app.portlets.PreviewCategoryPortlet</portlet-class>
		<init-param>
			<name>view-template</name>
			<value>/html/previewcategory/PreviewCategoryView.jsp</value>
		</init-param>
		<expiration-cache>0</expiration-cache>
		<supports>
			<mime-type>text/html</mime-type>
			<portlet-mode>view</portlet-mode>
		</supports>
		<resource-bundle>content/System</resource-bundle>
		<portlet-info>
			<title>Preview Category Portlet</title>
			<short-title>Preview Category Portlet</short-title>
			<keywords></keywords>
		</portlet-info>
		<security-role-ref>
			<role-name>administrator</role-name>
		</security-role-ref>
		<security-role-ref>
			<role-name>guest</role-name>
		</security-role-ref>
		<security-role-ref>
			<role-name>power-user</role-name>
		</security-role-ref>
		<security-role-ref>
			<role-name>user</role-name>
		</security-role-ref>
	</portlet> 
	 <portlet>
	 	<portlet-name>ordersummary</portlet-name>
	 	<display-name>Order Summary Portlet</display-name>
	 	<portlet-class>
	 		com.app.portlets.OrderSummaryPortlet
	 	</portlet-class>
	 	<init-param>
	 		<name>view-template</name>
	 		<value>/html/ordersummary/view.jsp</value>
	 	</init-param>
	 	<expiration-cache>0</expiration-cache>
	 	<supports>
	 		<mime-type>text/html</mime-type>
	 		<portlet-mode>view</portlet-mode>
	 	</supports>
	 	<resource-bundle>content/System</resource-bundle>
	 	<portlet-info>
	 		<title>Order Summary Portlet</title>
	 		<short-title>Order Summary Portlet</short-title>
	 		<keywords></keywords>
	 	</portlet-info>
	 	<security-role-ref>
	 		<role-name>administrator</role-name>
	 	</security-role-ref>
	 	<security-role-ref>
	 		<role-name>guest</role-name>
	 	</security-role-ref>
	 	<security-role-ref>
	 		<role-name>power-user</role-name>
	 	</security-role-ref>
	 	<security-role-ref>
	 		<role-name>user</role-name>
	 	</security-role-ref>
	 </portlet>
	 <portlet>
	 	<portlet-name>ccelogin</portlet-name>
	 	<display-name>CCE Login Portlet</display-name>
	 	<portlet-class>com.app.portlets.CCELoginPortlet</portlet-class>
	 	<init-param>
	 		<name>view-template</name>
	 		<value>/html/ccelogin/cceLoginView.jsp</value>
	 	</init-param>
	 	<expiration-cache>0</expiration-cache>
	 	<supports>
	 		<mime-type>text/html</mime-type>
	 		<portlet-mode>view</portlet-mode>
	 	</supports>
	 	<resource-bundle>content/System</resource-bundle>
	 	<portlet-info>
	 		<title>CCE Login Portlet</title>
	 		<short-title>CCE Login Portlet</short-title>
	 		<keywords></keywords>
	 	</portlet-info>
	 	<security-role-ref>
	 		<role-name>administrator</role-name>
	 	</security-role-ref>
	 	<security-role-ref>
	 		<role-name>guest</role-name>
	 	</security-role-ref>
	 	<security-role-ref>
	 		<role-name>power-user</role-name>
	 	</security-role-ref>
	 	<security-role-ref>
	 		<role-name>user</role-name>
	 	</security-role-ref>
	 </portlet>
	 <portlet>
	 	<portlet-name>categorystore</portlet-name>
	 	<display-name>Category Store</display-name>
	 	<portlet-class>com.app.portlets.CategoryStore</portlet-class>
	 	<init-param>
	 		<name>view-template</name>
	 		<value>/html/categorystore/categoryview.jsp</value>
	 	</init-param>
	 	<expiration-cache>0</expiration-cache>
	 	<supports>
	 		<mime-type>text/html</mime-type>
	 		<portlet-mode>view</portlet-mode>
	 	</supports>
	 	<resource-bundle>content/System</resource-bundle>
	 	<portlet-info>
	 		<title>Category Store</title>
	 		<short-title>Category Store</short-title>
	 		<keywords></keywords>
	 	</portlet-info>
	 	<security-role-ref>
	 		<role-name>administrator</role-name>
	 	</security-role-ref>
	 	<security-role-ref>
	 		<role-name>guest</role-name>
	 	</security-role-ref>
	 	<security-role-ref>
	 		<role-name>power-user</role-name>
	 	</security-role-ref>
	 	<security-role-ref>
	 		<role-name>user</role-name>
	 	</security-role-ref>
	 </portlet>
	 
	 <portlet>
	 	<portlet-name>category-products</portlet-name>
	 	<display-name>Category Products</display-name>
	 	<portlet-class>
	 		com.app.portlets.CategoryProducts
	 	</portlet-class>
	 	<init-param>
	 		<name>view-template</name>
	 		<value>/html/categoryproducts/view.jsp</value>
	 	</init-param>
	 	<expiration-cache>0</expiration-cache>
	 	<supports>
	 		<mime-type>text/html</mime-type>
	 		<portlet-mode>view</portlet-mode>
	 	</supports>
	 	<resource-bundle>content/System</resource-bundle>
	 	<portlet-info>
	 		<title>Category Products</title>
	 		<short-title>Category Products</short-title>
	 		<keywords></keywords>
	 	</portlet-info>
	 	<security-role-ref>
	 		<role-name>administrator</role-name>
	 	</security-role-ref>
	 	<security-role-ref>
	 		<role-name>guest</role-name>
	 	</security-role-ref>
	 	<security-role-ref>
	 		<role-name>power-user</role-name>
	 	</security-role-ref>
	 	<security-role-ref>
	 		<role-name>user</role-name>
	 	</security-role-ref>
	 </portlet>
</portlet-app>